src/__init__.py
src/ai_object.py
src/bound_box.py
src/containers.py
src/contents.py
src/file_header.py
src/geo_location.py
src/image.py
src/main.py
intelicity_library_exemple-0.0.2.dist-info/LICENSE
intelicity_library_exemple-0.0.2.dist-info/METADATA
intelicity_library_exemple-0.0.2.dist-info/WHEEL
intelicity_library_exemple-0.0.2.dist-info/top_level.txt
intelicity_library_exemple-0.0.2.dist-info/RECORD
