Metadata-Version: 2.1
Name: intelicity-library-exemple
Version: 0.0.2
Summary: a library for reading and managing data from the Intelicity server
Author: Me
Author-email: Felipe Rodrigues Peixoto da Silva <frps2003@gmail.com>
License: MIT
Project-URL: Homepage, https://inteli.city/
Project-URL: project, https://github.com/Comunalti/Intelicity_Library
Classifier: Programming Language :: Python :: 3
Classifier: License :: OSI Approved :: MIT License
Classifier: Operating System :: OS Independent
Requires-Python: >=3.7
License-File: LICENSE
